LICENSE
README.md
setup.py
QEventManager.egg-info/PKG-INFO
QEventManager.egg-info/SOURCES.txt
QEventManager.egg-info/dependency_links.txt
QEventManager.egg-info/requires.txt
QEventManager.egg-info/top_level.txt
qeventmanager/__init__.py
qeventmanager/handler.py
qeventmanager/logger.py
qeventmanager/manager.py
qeventmanager/qt.py
qeventmanager/que_thread.py
qeventmanager/tools/__init__.py
qeventmanager/tools/image.py