Metadata-Version: 2.4
Name: QEventManager
Version: 1.0.1
Summary: QEventManager使用多线程的方式对任务进行处理，qasync的另一个替代
Home-page: https://gitee.com/chiyaun/qevent-manager
Author: 赤鸢仙人
Author-email: 2640610281@qq.com
Project-URL: Project Homepage, https://gitee.com/chiyaun/qevent-manager
Project-URL: Documentation, https://gitee.com/chiyaun/qevent-manager/blob/master/README.md
Project-URL: Source Code, https://gitee.com/chiyaun/qevent-manager
Project-URL: Bug Tracker, https://gitee.com/chiyaun/qevent-manager/issues
Keywords: Qt事件处理
Platform: all
Classifier: Intended Audience :: Developers
Classifier: Operating System :: OS Independent
Classifier: Natural Language :: Chinese (Simplified)
Classifier: Programming Language :: Python
Classifier: Programming Language :: Python :: 3.8
Requires-Python: >=3.7
License-File: LICENSE
Requires-Dist: requests
Requires-Dist: pillow
Dynamic: author
Dynamic: author-email
Dynamic: classifier
Dynamic: description
Dynamic: description-content-type
Dynamic: home-page
Dynamic: keywords
Dynamic: license-file
Dynamic: platform
Dynamic: project-url
Dynamic: requires-dist
Dynamic: requires-python
Dynamic: summary
